{"assets":{"F2EEDCA0A03F2819DBDC1A58DC593C3C":{"type":"texture","index":0,"assetRequest":{"type":"slide","state":"contents","slide":"none"},"url":{"native":"assets\/27071D49-B617-4214-91DC-44AA5686B722.pdf"},"width":1920,"height":1080},"77AC3764EAF928C72E48A01CF55157B6":{"type":"texture","index":1,"assetRequest":{"type":"slide","state":"contents","slide":"none"},"url":{"native":"assets\/27071D49-B617-4214-91DC-44AA5686B722.pdf"},"width":1920,"height":1080}},"events":[{"effects":[{"beginTime":0,"baseLayer":{"animations":[],"initialState":{"affineTransform":[1,0,0,1,0,0],"masksToBounds":false,"rotation":0,"scale":1,"position":{"pointX":960,"pointY":540},"width":1920,"sublayerTransform":[1,0,0,0,0,1,0,0,0,0,1,0,0,0,0,1],"contentsRect":{"y":0,"x":0,"width":1,"height":1},"opacity":1,"edgeAntialiasingMask":251658240,"height":1080,"hidden":false,"anchorPoint":{"pointX":0.5,"pointY":0.5}},"objectID":"0","layers":[{"animations":[],"initialState":{"affineTransform":[1,0,0,1,0,0],"masksToBounds":false,"rotation":0,"scale":1,"position":{"pointX":960,"pointY":540},"width":1920,"sublayerTransform":[1,0,0,0,0,1,0,0,0,0,1,-0.00035007912466775983,0,0,0,1],"contentsRect":{"y":0,"x":0,"width":1,"height":1},"opacity":1,"edgeAntialiasingMask":251658240,"height":1080,"hidden":false,"anchorPoint":{"pointX":0.5,"pointY":0.5}},"layers":[{"animations":[],"layers":[],"texturedRectangle":{"isBackgroundTexture":false,"singleTextureOpacity":1,"textureType":0,"textBaseline":0,"textXHeight":0,"isVerticalText":false},"initialState":{"affineTransform":[1,0,0,1,0,0],"masksToBounds":false,"rotation":0,"scale":1,"position":{"pointX":960,"pointY":540},"width":1920,"sublayerTransform":[1,0,0,0,0,1,0,0,0,0,1,0,0,0,0,1],"contentsRect":{"y":0,"x":0,"width":1,"height":1},"opacity":1,"edgeAntialiasingMask":0,"height":1080,"hidden":false,"anchorPoint":{"pointX":0.5,"pointY":0.5}},"texture":"77AC3764EAF928C72E48A01CF55157B6"},{"animations":[{"additive":false,"timeOffset":0,"beginTime":0,"from":{"scalar":false},"repeatCount":0,"fillMode":"both","duration":0.01,"autoreverses":false,"property":"hidden","to":{"scalar":true},"removedOnCompletion":false}],"layers":[],"texturedRectangle":{"isBackgroundTexture":false,"singleTextureOpacity":1,"textureType":0,"textBaseline":0,"textXHeight":0,"isVerticalText":false},"initialState":{"affineTransform":[1,0,0,1,0,0],"masksToBounds":false,"rotation":0,"scale":1,"position":{"pointX":960,"pointY":540},"width":1920,"sublayerTransform":[1,0,0,0,0,1,0,0,0,0,1,0,0,0,0,1],"contentsRect":{"y":0,"x":0,"width":1,"height":1},"opacity":1,"edgeAntialiasingMask":0,"height":1080,"hidden":false,"anchorPoint":{"pointX":0.5,"pointY":0.5}},"texture":"F2EEDCA0A03F2819DBDC1A58DC593C3C"}]}]},"effects":[],"duration":0.01,"type":"transition","attributes":{"direction":0},"name":"none","objectID":"0"}],"automaticPlay":false,"hyperlinks":[],"accessibility":[{"text":"SpaceX Office Tour 2010, SpaceX YouTube","targetRectangle":{"y":925.46429449319839,"x":1406.220890045166,"width":461.08800000000019,"height":28.3280029296875}},{"text":"doors limit","targetRectangle":{"y":807.7660768032074,"x":1525.1618419870733,"width":242.45000024586943,"height":59.549652099609375}},{"text":"communication","targetRectangle":{"y":856.85614709317269,"x":1467.8118419647217,"width":357.15000029057273,"height":59.549652099609375}},{"text":"Abbau von Doppelstrukturen ","targetRectangle":{"y":338.52792358398438,"x":140.76000213623047,"width":573.15600000000006,"height":49.788669433593782}},{"text":"Nutzung agiler Projektteams statt „temporärer Arbeitsgruppen“","targetRectangle":{"y":384.54905545357065,"x":140.76000213623047,"width":1204.1078400000001,"height":88.938669648170446}},{"text":"Modernisierung der internen Kommunikationsmittel","targetRectangle":{"y":469.72018753773358,"x":140.76000213623047,"width":955.3435199999999,"height":87.980725312233005}},{"text":"Bündelung (und Ausbau) strategischer Kompetenzen","targetRectangle":{"y":553.98711407832945,"x":140.76000213623047,"width":996.22656000000006,"height":88.938669648170503}},{"text":"Statistik und Softwareentwicklung","targetRectangle":{"y":639.15824616249245,"x":188.76000213623047,"width":634.16736000000014,"height":87.980725312232948}},{"text":"Research Operations","targetRectangle":{"y":723.42517270308826,"x":188.76000213623047,"width":392.91984000000002,"height":87.980725312233062}},{"text":"Data Engineering und Data Mining","targetRectangle":{"y":807.6920992436842,"x":188.76000213623047,"width":638.17632000000015,"height":87.980725312233062}},{"text":"Modelling und Digital Story Telling","targetRectangle":{"y":891.95902578428013,"x":188.76000213623047,"width":632.66399999999987,"height":87.980725312233062}},{"text":"Organisation","targetRectangle":{"y":89,"x":99,"width":498.10000045597553,"height":100.53440856933594}},{"text":"Agile Teams, neue agile Fehlerkultur, Kompetenzcluster","targetRectangle":{"y":190.44745779037476,"x":98.599999904632568,"width":1453.0450000000001,"height":66.404617309570312}},{"text":"Bildschirmfoto 2021-04-28 um 22.26.06.png","targetRectangle":{"y":453.62060546875,"x":1500.4183349609375,"width":291.9368896484375,"height":350.08697509765625}}],"baseLayer":{"animations":[],"initialState":{"affineTransform":[1,0,0,1,0,0],"masksToBounds":false,"rotation":0,"scale":1,"position":{"pointX":960,"pointY":540},"width":1920,"sublayerTransform":[1,0,0,0,0,1,0,0,0,0,1,0,0,0,0,1],"contentsRect":{"y":0,"x":0,"width":1,"height":1},"opacity":1,"edgeAntialiasingMask":251658240,"height":1080,"hidden":false,"anchorPoint":{"pointX":0.5,"pointY":0.5}},"objectID":"0","layers":[{"animations":[],"initialState":{"affineTransform":[1,0,0,1,0,0],"masksToBounds":false,"rotation":0,"scale":1,"position":{"pointX":960,"pointY":540},"width":1920,"sublayerTransform":[1,0,0,0,0,1,0,0,0,0,1,-0.00035007912466775983,0,0,0,1],"contentsRect":{"y":0,"x":0,"width":1,"height":1},"opacity":1,"edgeAntialiasingMask":251658240,"height":1080,"hidden":false,"anchorPoint":{"pointX":0.5,"pointY":0.5}},"layers":[{"animations":[],"layers":[],"texturedRectangle":{"isBackgroundTexture":false,"singleTextureOpacity":1,"textureType":0,"textBaseline":0,"textXHeight":0,"isVerticalText":false},"initialState":{"affineTransform":[1,0,0,1,0,0],"masksToBounds":false,"rotation":0,"scale":1,"position":{"pointX":960,"pointY":540},"width":1920,"sublayerTransform":[1,0,0,0,0,1,0,0,0,0,1,0,0,0,0,1],"contentsRect":{"y":0,"x":0,"width":1,"height":1},"opacity":1,"edgeAntialiasingMask":0,"height":1080,"hidden":false,"anchorPoint":{"pointX":0.5,"pointY":0.5}},"texture":"F2EEDCA0A03F2819DBDC1A58DC593C3C"}]}]}}]}